affinidi_tdk_credential_verification_client/__init__.py
affinidi_tdk_credential_verification_client/api/__init__.py
affinidi_tdk_credential_verification_client/api/default_api.py
affinidi_tdk_credential_verification_client/api_client.py
affinidi_tdk_credential_verification_client/api_response.py
affinidi_tdk_credential_verification_client/configuration.py
affinidi_tdk_credential_verification_client/exceptions.py
affinidi_tdk_credential_verification_client/models/__init__.py
affinidi_tdk_credential_verification_client/models/constraints.py
affinidi_tdk_credential_verification_client/models/constraints_statuses.py
affinidi_tdk_credential_verification_client/models/descriptor.py
affinidi_tdk_credential_verification_client/models/error.py
affinidi_tdk_credential_verification_client/models/error_detail.py
affinidi_tdk_credential_verification_client/models/evaluate_vp_output.py
affinidi_tdk_credential_verification_client/models/field.py
affinidi_tdk_credential_verification_client/models/filter.py
affinidi_tdk_credential_verification_client/models/filter_const.py
affinidi_tdk_credential_verification_client/models/filter_items.py
affinidi_tdk_credential_verification_client/models/format.py
affinidi_tdk_credential_verification_client/models/holder_subject.py
affinidi_tdk_credential_verification_client/models/input_descriptor.py
affinidi_tdk_credential_verification_client/models/invalid_parameter_error.py
affinidi_tdk_credential_verification_client/models/jwt_object.py
affinidi_tdk_credential_verification_client/models/ldp_object.py
affinidi_tdk_credential_verification_client/models/nested_descriptor.py
affinidi_tdk_credential_verification_client/models/not_found_error.py
affinidi_tdk_credential_verification_client/models/not_found_error_details_inner.py
affinidi_tdk_credential_verification_client/models/pd_status.py
affinidi_tdk_credential_verification_client/models/presentation_definition.py
affinidi_tdk_credential_verification_client/models/presentation_submission.py
affinidi_tdk_credential_verification_client-1.61.0.dist-info/METADATA
affinidi_tdk_credential_verification_client-1.61.0.dist-info/WHEEL
affinidi_tdk_credential_verification_client-1.61.0.dist-info/RECORD
